README.md
setup.py
swagger_client/__init__.py
swagger_client/api_client.py
swagger_client/configuration.py
swagger_client/rest.py
swagger_client/api/__init__.py
swagger_client/api/accounting_codes_api.py
swagger_client/api/accounting_periods_api.py
swagger_client/api/accounts_api.py
swagger_client/api/actions_api.py
swagger_client/api/adjustments_api.py
swagger_client/api/aggregate_queries_api.py
swagger_client/api/api_health_api.py
swagger_client/api/attachments_api.py
swagger_client/api/bill_run_api.py
swagger_client/api/bill_run_health_api.py
swagger_client/api/billing_documents_api.py
swagger_client/api/billing_preview_run_api.py
swagger_client/api/catalog_api.py
swagger_client/api/catalog_groups_api.py
swagger_client/api/configuration_templates_api.py
swagger_client/api/contact_snapshots_api.py
swagger_client/api/contacts_api.py
swagger_client/api/credit_memos_api.py
swagger_client/api/custom_event_triggers_api.py
swagger_client/api/custom_exchange_rates_api.py
swagger_client/api/custom_object_definitions_api.py
swagger_client/api/custom_object_jobs_api.py
swagger_client/api/custom_object_records_api.py
swagger_client/api/custom_payment_method_types_api.py
swagger_client/api/custom_scheduled_events_api.py
swagger_client/api/data_queries_api.py
swagger_client/api/debit_memos_api.py
swagger_client/api/describe_api.py
swagger_client/api/electronic_payments_health_api.py
swagger_client/api/files_api.py
swagger_client/api/fulfillments_api.py
swagger_client/api/hosted_pages_api.py
swagger_client/api/imports_api.py
swagger_client/api/invoice_schedules_api.py
swagger_client/api/invoices_api.py
swagger_client/api/journal_runs_api.py
swagger_client/api/mass_updater_api.py
swagger_client/api/notifications_api.py
swagger_client/api/o_auth_api.py
swagger_client/api/offers_api.py
swagger_client/api/operations_api.py
swagger_client/api/order_actions_api.py
swagger_client/api/order_line_items_api.py
swagger_client/api/orders_api.py
zuora_swagger_client.egg-info/PKG-INFO
zuora_swagger_client.egg-info/SOURCES.txt
zuora_swagger_client.egg-info/dependency_links.txt
zuora_swagger_client.egg-info/requires.txt
zuora_swagger_client.egg-info/top_level.txt