Metadata-Version: 2.1
Name: zuora-swagger-client
Version: 1.2.0
Summary: API Reference
Home-page: 
Author-email: docs@zuora.com
Keywords: Swagger,API Reference
